pyomnilogic_local/__init__.py
pyomnilogic_local/_base.py
pyomnilogic_local/api/__init__.py
pyomnilogic_local/api/api.py
pyomnilogic_local/api/constants.py
pyomnilogic_local/api/exceptions.py
pyomnilogic_local/api/protocol.py
pyomnilogic_local/backyard.py
pyomnilogic_local/bow.py
pyomnilogic_local/chlorinator.py
pyomnilogic_local/chlorinator_equip.py
pyomnilogic_local/cli/__init__.py
pyomnilogic_local/cli/cli.py
pyomnilogic_local/cli/debug/__init__.py
pyomnilogic_local/cli/debug/commands.py
pyomnilogic_local/cli/get/__init__.py
pyomnilogic_local/cli/get/backyard.py
pyomnilogic_local/cli/get/bows.py
pyomnilogic_local/cli/get/chlorinators.py
pyomnilogic_local/cli/get/commands.py
pyomnilogic_local/cli/get/csads.py
pyomnilogic_local/cli/get/filters.py
pyomnilogic_local/cli/get/groups.py
pyomnilogic_local/cli/get/heaters.py
pyomnilogic_local/cli/get/lights.py
pyomnilogic_local/cli/get/pumps.py
pyomnilogic_local/cli/get/relays.py
pyomnilogic_local/cli/get/schedules.py
pyomnilogic_local/cli/get/sensors.py
pyomnilogic_local/cli/get/valves.py
pyomnilogic_local/cli/pcap_utils.py
pyomnilogic_local/cli/utils.py
pyomnilogic_local/collections.py
pyomnilogic_local/colorlogiclight.py
pyomnilogic_local/csad.py
pyomnilogic_local/csad_equip.py
pyomnilogic_local/decorators.py
pyomnilogic_local/filter.py
pyomnilogic_local/groups.py
pyomnilogic_local/heater.py
pyomnilogic_local/heater_equip.py
pyomnilogic_local/models/__init__.py
pyomnilogic_local/models/const.py
pyomnilogic_local/models/exceptions.py
pyomnilogic_local/models/filter_diagnostics.py
pyomnilogic_local/models/leadmessage.py
pyomnilogic_local/models/mspconfig.py
pyomnilogic_local/models/telemetry.py
pyomnilogic_local/omnilogic.py
pyomnilogic_local/omnitypes.py
pyomnilogic_local/pump.py
pyomnilogic_local/py.typed
pyomnilogic_local/relay.py
pyomnilogic_local/schedule.py
pyomnilogic_local/sensor.py
pyomnilogic_local/system.py
pyomnilogic_local/util.py
python_omnilogic_local-0.20.8.dist-info/licenses/LICENSE
python_omnilogic_local-0.20.8.dist-info/WHEEL
python_omnilogic_local-0.20.8.dist-info/entry_points.txt
python_omnilogic_local-0.20.8.dist-info/METADATA
python_omnilogic_local-0.20.8.dist-info/RECORD
