Metadata-Version: 2.4
Name: python-omnilogic-local
Version: 0.20.8
Summary: A library for local control of Hayward OmniHub/OmniLogic pool controllers using their local API
Author: Chris Jowett, djtimca, garionphx
Author-email: Chris Jowett <421501+cryptk@users.noreply.github.com>
License-File: LICENSE
Requires-Dist: pydantic>=2.0.0,<3.0.0
Requires-Dist: click>=8.0.0,<9.0.0
Requires-Dist: xmltodict>=1.0.1,<2.0.0
Requires-Dist: uv~=0.9.8 ; extra == 'build'
Requires-Dist: scapy>=2.6.1,<3.0.0 ; extra == 'cli'
Requires-Python: >=3.13, <4.0.0
Provides-Extra: build
Provides-Extra: cli
